{
  "schema_version": "1.0.0",
  "personas": [
    {
      "id": "persona_neutral",
      "display_name": "Neutral",
      "subtitle": "Default reasoning stance",
      "category": "baseline",
      "when_to_use": "Use as an unframed baseline for study comparisons.",
      "default": true,
      "sort_order": 0
    },
    {
      "id": "persona_skeptical",
      "display_name": "Skeptical",
      "subtitle": "Strongest-objection framing",
      "category": "adversarial",
      "when_to_use": "Use when you want pressure against premature conclusions.",
      "default": false,
      "sort_order": 1
    },
    {
      "id": "persona_precise",
      "display_name": "Precise",
      "subtitle": "Explicit terms and assumptions",
      "category": "analytical",
      "when_to_use": "Use when exact terms and assumptions must stay explicit.",
      "default": false,
      "sort_order": 2
    },
    {
      "id": "persona_exploratory",
      "display_name": "Exploratory",
      "subtitle": "Multiple approaches before committing",
      "category": "divergent",
      "when_to_use": "Use when exploring multiple approaches matters first.",
      "default": false,
      "sort_order": 3
    }
  ]
}
